cardano_py_tools/__init__.py
cardano_py_tools/transaction.py
cardano_py_tools/util.py
cardano_py_tools-0.1b0.dist-info/LICENSE
cardano_py_tools-0.1b0.dist-info/METADATA
cardano_py_tools-0.1b0.dist-info/WHEEL
cardano_py_tools-0.1b0.dist-info/top_level.txt
cardano_py_tools-0.1b0.dist-info/RECORD
